odoo/addons/product_customerinfo_elaboration/README.rst
odoo/addons/product_customerinfo_elaboration/__init__.py
odoo/addons/product_customerinfo_elaboration/__manifest__.py
odoo/addons/product_customerinfo_elaboration/i18n/es.po
odoo/addons/product_customerinfo_elaboration/i18n/it.po
odoo/addons/product_customerinfo_elaboration/i18n/product_customerinfo_elaboration.pot
odoo/addons/product_customerinfo_elaboration/i18n/product_supplierinfo_for_customer_elaboration.pot
odoo/addons/product_customerinfo_elaboration/models/__init__.py
odoo/addons/product_customerinfo_elaboration/models/product_customerinfo.py
odoo/addons/product_customerinfo_elaboration/models/sale_order_line.py
odoo/addons/product_customerinfo_elaboration/readme/CONFIGURE.md
odoo/addons/product_customerinfo_elaboration/readme/CONTRIBUTORS.md
odoo/addons/product_customerinfo_elaboration/readme/DESCRIPTION.md
odoo/addons/product_customerinfo_elaboration/readme/USAGE.md
odoo/addons/product_customerinfo_elaboration/security/ir.model.access.csv
odoo/addons/product_customerinfo_elaboration/static/description/icon.png
odoo/addons/product_customerinfo_elaboration/static/description/index.html
odoo/addons/product_customerinfo_elaboration/tests/__init__.py
odoo/addons/product_customerinfo_elaboration/tests/test_customerinfo_elaboration.py
odoo/addons/product_customerinfo_elaboration/views/product_views.xml
odoo_addon_product_customerinfo_elaboration-18.0.1.0.0.4.dist-info/METADATA
odoo_addon_product_customerinfo_elaboration-18.0.1.0.0.4.dist-info/WHEEL
odoo_addon_product_customerinfo_elaboration-18.0.1.0.0.4.dist-info/top_level.txt
odoo_addon_product_customerinfo_elaboration-18.0.1.0.0.4.dist-info/RECORD
