Metadata-Version: 2.1
Name: odoo-addon-product_customerinfo_elaboration
Version: 18.0.1.0.0.4
Requires-Python: >=3.10
Requires-Dist: odoo-addon-product_customerinfo_sale==18.0.*
Requires-Dist: odoo-addon-sale_elaboration==18.0.*
Requires-Dist: odoo==18.0.*
Summary: Allows to define default elaborations and elaboration notes on product customerinfos
Home-page: https://github.com/OCA/sale-workflow
License: AGPL-3
Author: Tecnativa, Odoo Community Association (OCA)
Author-email: support@odoo-community.org
Classifier: Programming Language :: Python
Classifier: Framework :: Odoo
Classifier: Framework :: Odoo :: 18.0
Classifier: License :: OSI Approved :: GNU Affero General Public License v3
Classifier: Development Status :: 4 - Beta
